<annotation>
  <folder>VOC2007</folder>
  <filename>darmstadt_000047_000019.png</filename>
  <size>
    <width>2048</width>
    <height>1024</height>
    <depth>3</depth>
  </size>
  <object>
    <name>pedestrian</name>
    <pose>Unspecified</pose>
    <difficult>0</difficult>
    <truncated>0</truncated>
    <bndbox>
      <xmin>1100</xmin>
      <ymin>423</ymin>
      <xmax>1118</xmax>
      <ymax>466</ymax>
    </bndbox>
  </object>
  <object>
    <name>pedestrian</name>
    <pose>Unspecified</pose>
    <difficult>0</difficult>
    <truncated>0</truncated>
    <bndbox>
      <xmin>1231</xmin>
      <ymin>422</ymin>
      <xmax>1243</xmax>
      <ymax>453</ymax>
    </bndbox>
  </object>
  <object>
    <name>pedestrian</name>
    <pose>Unspecified</pose>
    <difficult>0</difficult>
    <truncated>0</truncated>
    <bndbox>
      <xmin>1324</xmin>
      <ymin>417</ymin>
      <xmax>1344</xmax>
      <ymax>466</ymax>
    </bndbox>
  </object>
</annotation>
