<annotation>
  <folder>VOC2007</folder>
  <filename>hamburg_000000_007737.png</filename>
  <size>
    <width>2048</width>
    <height>1024</height>
    <depth>3</depth>
  </size>
  <object>
    <name>pedestrian</name>
    <pose>Unspecified</pose>
    <difficult>0</difficult>
    <truncated>0</truncated>
    <bndbox>
      <xmin>719</xmin>
      <ymin>338</ymin>
      <xmax>809</xmax>
      <ymax>558</ymax>
    </bndbox>
  </object>
  <object>
    <name>pedestrian</name>
    <pose>Unspecified</pose>
    <difficult>0</difficult>
    <truncated>0</truncated>
    <bndbox>
      <xmin>1611</xmin>
      <ymin>378</ymin>
      <xmax>1628</xmax>
      <ymax>422</ymax>
    </bndbox>
  </object>
  <object>
    <name>pedestrian</name>
    <pose>Unspecified</pose>
    <difficult>0</difficult>
    <truncated>1</truncated>
    <bndbox>
      <xmin>1607</xmin>
      <ymin>391</ymin>
      <xmax>1623</xmax>
      <ymax>404</ymax>
    </bndbox>
  </object>
  <object>
    <name>pedestrian</name>
    <pose>Unspecified</pose>
    <difficult>0</difficult>
    <truncated>1</truncated>
    <bndbox>
      <xmin>1624</xmin>
      <ymin>388</ymin>
      <xmax>1638</xmax>
      <ymax>403</ymax>
    </bndbox>
  </object>
</annotation>
