<annotation>
  <folder>VOC2007</folder>
  <filename>hamburg_000000_046872.png</filename>
  <size>
    <width>2048</width>
    <height>1024</height>
    <depth>3</depth>
  </size>
  <object>
    <name>pedestrian</name>
    <pose>Unspecified</pose>
    <difficult>0</difficult>
    <truncated>1</truncated>
    <bndbox>
      <xmin>1565</xmin>
      <ymin>396</ymin>
      <xmax>1579</xmax>
      <ymax>409</ymax>
    </bndbox>
  </object>
  <object>
    <name>pedestrian</name>
    <pose>Unspecified</pose>
    <difficult>0</difficult>
    <truncated>1</truncated>
    <bndbox>
      <xmin>1588</xmin>
      <ymin>397</ymin>
      <xmax>1604</xmax>
      <ymax>417</ymax>
    </bndbox>
  </object>
  <object>
    <name>pedestrian</name>
    <pose>Unspecified</pose>
    <difficult>0</difficult>
    <truncated>0</truncated>
    <bndbox>
      <xmin>1664</xmin>
      <ymin>368</ymin>
      <xmax>1688</xmax>
      <ymax>428</ymax>
    </bndbox>
  </object>
  <object>
    <name>pedestrian</name>
    <pose>Unspecified</pose>
    <difficult>0</difficult>
    <truncated>1</truncated>
    <bndbox>
      <xmin>1650</xmin>
      <ymin>373</ymin>
      <xmax>1672</xmax>
      <ymax>429</ymax>
    </bndbox>
  </object>
  <object>
    <name>pedestrian</name>
    <pose>Unspecified</pose>
    <difficult>0</difficult>
    <truncated>0</truncated>
    <bndbox>
      <xmin>1688</xmin>
      <ymin>358</ymin>
      <xmax>1716</xmax>
      <ymax>427</ymax>
    </bndbox>
  </object>
  <object>
    <name>pedestrian</name>
    <pose>Unspecified</pose>
    <difficult>0</difficult>
    <truncated>0</truncated>
    <bndbox>
      <xmin>1720</xmin>
      <ymin>341</ymin>
      <xmax>1757</xmax>
      <ymax>433</ymax>
    </bndbox>
  </object>
  <object>
    <name>pedestrian</name>
    <pose>Unspecified</pose>
    <difficult>0</difficult>
    <truncated>0</truncated>
    <bndbox>
      <xmin>1691</xmin>
      <ymin>351</ymin>
      <xmax>1726</xmax>
      <ymax>437</ymax>
    </bndbox>
  </object>
  <object>
    <name>pedestrian</name>
    <pose>Unspecified</pose>
    <difficult>0</difficult>
    <truncated>0</truncated>
    <bndbox>
      <xmin>1747</xmin>
      <ymin>343</ymin>
      <xmax>1782</xmax>
      <ymax>431</ymax>
    </bndbox>
  </object>
  <object>
    <name>pedestrian</name>
    <pose>Unspecified</pose>
    <difficult>0</difficult>
    <truncated>0</truncated>
    <bndbox>
      <xmin>1734</xmin>
      <ymin>345</ymin>
      <xmax>1786</xmax>
      <ymax>472</ymax>
    </bndbox>
  </object>
  <object>
    <name>pedestrian</name>
    <pose>Unspecified</pose>
    <difficult>0</difficult>
    <truncated>0</truncated>
    <bndbox>
      <xmin>1782</xmin>
      <ymin>352</ymin>
      <xmax>1811</xmax>
      <ymax>424</ymax>
    </bndbox>
  </object>
  <object>
    <name>pedestrian</name>
    <pose>Unspecified</pose>
    <difficult>0</difficult>
    <truncated>0</truncated>
    <bndbox>
      <xmin>1815</xmin>
      <ymin>360</ymin>
      <xmax>1840</xmax>
      <ymax>421</ymax>
    </bndbox>
  </object>
  <object>
    <name>pedestrian</name>
    <pose>Unspecified</pose>
    <difficult>0</difficult>
    <truncated>0</truncated>
    <bndbox>
      <xmin>1828</xmin>
      <ymin>353</ymin>
      <xmax>1856</xmax>
      <ymax>425</ymax>
    </bndbox>
  </object>
  <object>
    <name>pedestrian</name>
    <pose>Unspecified</pose>
    <difficult>0</difficult>
    <truncated>0</truncated>
    <bndbox>
      <xmin>1789</xmin>
      <ymin>349</ymin>
      <xmax>1819</xmax>
      <ymax>424</ymax>
    </bndbox>
  </object>
  <object>
    <name>pedestrian</name>
    <pose>Unspecified</pose>
    <difficult>0</difficult>
    <truncated>0</truncated>
    <bndbox>
      <xmin>1854</xmin>
      <ymin>336</ymin>
      <xmax>1892</xmax>
      <ymax>431</ymax>
    </bndbox>
  </object>
  <object>
    <name>pedestrian</name>
    <pose>Unspecified</pose>
    <difficult>0</difficult>
    <truncated>0</truncated>
    <bndbox>
      <xmin>1882</xmin>
      <ymin>344</ymin>
      <xmax>1921</xmax>
      <ymax>440</ymax>
    </bndbox>
  </object>
  <object>
    <name>pedestrian</name>
    <pose>Unspecified</pose>
    <difficult>0</difficult>
    <truncated>0</truncated>
    <bndbox>
      <xmin>1917</xmin>
      <ymin>339</ymin>
      <xmax>1956</xmax>
      <ymax>436</ymax>
    </bndbox>
  </object>
  <object>
    <name>pedestrian</name>
    <pose>Unspecified</pose>
    <difficult>0</difficult>
    <truncated>0</truncated>
    <bndbox>
      <xmin>1902</xmin>
      <ymin>343</ymin>
      <xmax>1942</xmax>
      <ymax>442</ymax>
    </bndbox>
  </object>
  <object>
    <name>pedestrian</name>
    <pose>Unspecified</pose>
    <difficult>0</difficult>
    <truncated>0</truncated>
    <bndbox>
      <xmin>1936</xmin>
      <ymin>348</ymin>
      <xmax>1970</xmax>
      <ymax>434</ymax>
    </bndbox>
  </object>
  <object>
    <name>pedestrian</name>
    <pose>Unspecified</pose>
    <difficult>0</difficult>
    <truncated>0</truncated>
    <bndbox>
      <xmin>1952</xmin>
      <ymin>337</ymin>
      <xmax>1991</xmax>
      <ymax>435</ymax>
    </bndbox>
  </object>
  <object>
    <name>pedestrian</name>
    <pose>Unspecified</pose>
    <difficult>0</difficult>
    <truncated>1</truncated>
    <bndbox>
      <xmin>1956</xmin>
      <ymin>338</ymin>
      <xmax>1999</xmax>
      <ymax>443</ymax>
    </bndbox>
  </object>
  <object>
    <name>pedestrian</name>
    <pose>Unspecified</pose>
    <difficult>0</difficult>
    <truncated>0</truncated>
    <bndbox>
      <xmin>1930</xmin>
      <ymin>341</ymin>
      <xmax>1975</xmax>
      <ymax>451</ymax>
    </bndbox>
  </object>
  <object>
    <name>pedestrian</name>
    <pose>Unspecified</pose>
    <difficult>0</difficult>
    <truncated>0</truncated>
    <bndbox>
      <xmin>2027</xmin>
      <ymin>342</ymin>
      <xmax>2047</xmax>
      <ymax>424</ymax>
    </bndbox>
  </object>
  <object>
    <name>pedestrian</name>
    <pose>Unspecified</pose>
    <difficult>0</difficult>
    <truncated>0</truncated>
    <bndbox>
      <xmin>2008</xmin>
      <ymin>342</ymin>
      <xmax>2039</xmax>
      <ymax>420</ymax>
    </bndbox>
  </object>
  <object>
    <name>pedestrian</name>
    <pose>Unspecified</pose>
    <difficult>0</difficult>
    <truncated>0</truncated>
    <bndbox>
      <xmin>1960</xmin>
      <ymin>338</ymin>
      <xmax>2021</xmax>
      <ymax>487</ymax>
    </bndbox>
  </object>
  <object>
    <name>pedestrian</name>
    <pose>Unspecified</pose>
    <difficult>0</difficult>
    <truncated>0</truncated>
    <bndbox>
      <xmin>1972</xmin>
      <ymin>334</ymin>
      <xmax>2038</xmax>
      <ymax>496</ymax>
    </bndbox>
  </object>
  <object>
    <name>pedestrian</name>
    <pose>Unspecified</pose>
    <difficult>0</difficult>
    <truncated>0</truncated>
    <bndbox>
      <xmin>1789</xmin>
      <ymin>356</ymin>
      <xmax>1839</xmax>
      <ymax>478</ymax>
    </bndbox>
  </object>
  <object>
    <name>pedestrian</name>
    <pose>Unspecified</pose>
    <difficult>0</difficult>
    <truncated>0</truncated>
    <bndbox>
      <xmin>1420</xmin>
      <ymin>389</ymin>
      <xmax>1437</xmax>
      <ymax>430</ymax>
    </bndbox>
  </object>
  <object>
    <name>pedestrian</name>
    <pose>Unspecified</pose>
    <difficult>0</difficult>
    <truncated>0</truncated>
    <bndbox>
      <xmin>1324</xmin>
      <ymin>392</ymin>
      <xmax>1339</xmax>
      <ymax>430</ymax>
    </bndbox>
  </object>
  <object>
    <name>pedestrian</name>
    <pose>Unspecified</pose>
    <difficult>0</difficult>
    <truncated>0</truncated>
    <bndbox>
      <xmin>1279</xmin>
      <ymin>391</ymin>
      <xmax>1295</xmax>
      <ymax>431</ymax>
    </bndbox>
  </object>
  <object>
    <name>pedestrian</name>
    <pose>Unspecified</pose>
    <difficult>0</difficult>
    <truncated>0</truncated>
    <bndbox>
      <xmin>1264</xmin>
      <ymin>386</ymin>
      <xmax>1282</xmax>
      <ymax>431</ymax>
    </bndbox>
  </object>
  <object>
    <name>pedestrian</name>
    <pose>Unspecified</pose>
    <difficult>0</difficult>
    <truncated>0</truncated>
    <bndbox>
      <xmin>1237</xmin>
      <ymin>393</ymin>
      <xmax>1252</xmax>
      <ymax>431</ymax>
    </bndbox>
  </object>
  <object>
    <name>pedestrian</name>
    <pose>Unspecified</pose>
    <difficult>0</difficult>
    <truncated>0</truncated>
    <bndbox>
      <xmin>1224</xmin>
      <ymin>394</ymin>
      <xmax>1237</xmax>
      <ymax>426</ymax>
    </bndbox>
  </object>
  <object>
    <name>pedestrian</name>
    <pose>Unspecified</pose>
    <difficult>0</difficult>
    <truncated>0</truncated>
    <bndbox>
      <xmin>1211</xmin>
      <ymin>391</ymin>
      <xmax>1225</xmax>
      <ymax>427</ymax>
    </bndbox>
  </object>
  <object>
    <name>pedestrian</name>
    <pose>Unspecified</pose>
    <difficult>0</difficult>
    <truncated>0</truncated>
    <bndbox>
      <xmin>1194</xmin>
      <ymin>393</ymin>
      <xmax>1210</xmax>
      <ymax>433</ymax>
    </bndbox>
  </object>
  <object>
    <name>pedestrian</name>
    <pose>Unspecified</pose>
    <difficult>0</difficult>
    <truncated>0</truncated>
    <bndbox>
      <xmin>1208</xmin>
      <ymin>400</ymin>
      <xmax>1222</xmax>
      <ymax>434</ymax>
    </bndbox>
  </object>
  <object>
    <name>pedestrian</name>
    <pose>Unspecified</pose>
    <difficult>0</difficult>
    <truncated>1</truncated>
    <bndbox>
      <xmin>1216</xmin>
      <ymin>409</ymin>
      <xmax>1224</xmax>
      <ymax>431</ymax>
    </bndbox>
  </object>
  <object>
    <name>pedestrian</name>
    <pose>Unspecified</pose>
    <difficult>0</difficult>
    <truncated>1</truncated>
    <bndbox>
      <xmin>710</xmin>
      <ymin>419</ymin>
      <xmax>721</xmax>
      <ymax>445</ymax>
    </bndbox>
  </object>
  <object>
    <name>pedestrian</name>
    <pose>Unspecified</pose>
    <difficult>0</difficult>
    <truncated>0</truncated>
    <bndbox>
      <xmin>695</xmin>
      <ymin>417</ymin>
      <xmax>707</xmax>
      <ymax>449</ymax>
    </bndbox>
  </object>
  <object>
    <name>pedestrian</name>
    <pose>Unspecified</pose>
    <difficult>0</difficult>
    <truncated>0</truncated>
    <bndbox>
      <xmin>680</xmin>
      <ymin>428</ymin>
      <xmax>688</xmax>
      <ymax>448</ymax>
    </bndbox>
  </object>
  <object>
    <name>pedestrian</name>
    <pose>Unspecified</pose>
    <difficult>0</difficult>
    <truncated>0</truncated>
    <bndbox>
      <xmin>670</xmin>
      <ymin>431</ymin>
      <xmax>676</xmax>
      <ymax>448</ymax>
    </bndbox>
  </object>
  <object>
    <name>pedestrian</name>
    <pose>Unspecified</pose>
    <difficult>0</difficult>
    <truncated>0</truncated>
    <bndbox>
      <xmin>662</xmin>
      <ymin>429</ymin>
      <xmax>670</xmax>
      <ymax>448</ymax>
    </bndbox>
  </object>
  <object>
    <name>pedestrian</name>
    <pose>Unspecified</pose>
    <difficult>0</difficult>
    <truncated>0</truncated>
    <bndbox>
      <xmin>638</xmin>
      <ymin>419</ymin>
      <xmax>649</xmax>
      <ymax>446</ymax>
    </bndbox>
  </object>
  <object>
    <name>pedestrian</name>
    <pose>Unspecified</pose>
    <difficult>0</difficult>
    <truncated>1</truncated>
    <bndbox>
      <xmin>646</xmin>
      <ymin>413</ymin>
      <xmax>659</xmax>
      <ymax>448</ymax>
    </bndbox>
  </object>
  <object>
    <name>pedestrian</name>
    <pose>Unspecified</pose>
    <difficult>0</difficult>
    <truncated>1</truncated>
    <bndbox>
      <xmin>601</xmin>
      <ymin>416</ymin>
      <xmax>614</xmax>
      <ymax>449</ymax>
    </bndbox>
  </object>
  <object>
    <name>pedestrian</name>
    <pose>Unspecified</pose>
    <difficult>0</difficult>
    <truncated>1</truncated>
    <bndbox>
      <xmin>606</xmin>
      <ymin>398</ymin>
      <xmax>627</xmax>
      <ymax>449</ymax>
    </bndbox>
  </object>
  <object>
    <name>pedestrian</name>
    <pose>Unspecified</pose>
    <difficult>0</difficult>
    <truncated>1</truncated>
    <bndbox>
      <xmin>628</xmin>
      <ymin>413</ymin>
      <xmax>642</xmax>
      <ymax>449</ymax>
    </bndbox>
  </object>
  <object>
    <name>pedestrian</name>
    <pose>Unspecified</pose>
    <difficult>0</difficult>
    <truncated>0</truncated>
    <bndbox>
      <xmin>580</xmin>
      <ymin>416</ymin>
      <xmax>594</xmax>
      <ymax>450</ymax>
    </bndbox>
  </object>
  <object>
    <name>pedestrian</name>
    <pose>Unspecified</pose>
    <difficult>0</difficult>
    <truncated>0</truncated>
    <bndbox>
      <xmin>556</xmin>
      <ymin>398</ymin>
      <xmax>577</xmax>
      <ymax>450</ymax>
    </bndbox>
  </object>
  <object>
    <name>pedestrian</name>
    <pose>Unspecified</pose>
    <difficult>0</difficult>
    <truncated>0</truncated>
    <bndbox>
      <xmin>451</xmin>
      <ymin>414</ymin>
      <xmax>466</xmax>
      <ymax>451</ymax>
    </bndbox>
  </object>
  <object>
    <name>pedestrian</name>
    <pose>Unspecified</pose>
    <difficult>0</difficult>
    <truncated>1</truncated>
    <bndbox>
      <xmin>465</xmin>
      <ymin>401</ymin>
      <xmax>485</xmax>
      <ymax>451</ymax>
    </bndbox>
  </object>
  <object>
    <name>pedestrian</name>
    <pose>Unspecified</pose>
    <difficult>0</difficult>
    <truncated>0</truncated>
    <bndbox>
      <xmin>482</xmin>
      <ymin>392</ymin>
      <xmax>505</xmax>
      <ymax>451</ymax>
    </bndbox>
  </object>
  <object>
    <name>pedestrian</name>
    <pose>Unspecified</pose>
    <difficult>0</difficult>
    <truncated>1</truncated>
    <bndbox>
      <xmin>426</xmin>
      <ymin>404</ymin>
      <xmax>445</xmax>
      <ymax>452</ymax>
    </bndbox>
  </object>
  <object>
    <name>pedestrian</name>
    <pose>Unspecified</pose>
    <difficult>0</difficult>
    <truncated>0</truncated>
    <bndbox>
      <xmin>393</xmin>
      <ymin>404</ymin>
      <xmax>412</xmax>
      <ymax>452</ymax>
    </bndbox>
  </object>
  <object>
    <name>pedestrian</name>
    <pose>Unspecified</pose>
    <difficult>0</difficult>
    <truncated>0</truncated>
    <bndbox>
      <xmin>363</xmin>
      <ymin>384</ymin>
      <xmax>397</xmax>
      <ymax>469</ymax>
    </bndbox>
  </object>
  <object>
    <name>pedestrian</name>
    <pose>Unspecified</pose>
    <difficult>0</difficult>
    <truncated>0</truncated>
    <bndbox>
      <xmin>338</xmin>
      <ymin>381</ymin>
      <xmax>374</xmax>
      <ymax>469</ymax>
    </bndbox>
  </object>
  <object>
    <name>pedestrian</name>
    <pose>Unspecified</pose>
    <difficult>0</difficult>
    <truncated>0</truncated>
    <bndbox>
      <xmin>282</xmin>
      <ymin>401</ymin>
      <xmax>303</xmax>
      <ymax>454</ymax>
    </bndbox>
  </object>
  <object>
    <name>pedestrian</name>
    <pose>Unspecified</pose>
    <difficult>0</difficult>
    <truncated>0</truncated>
    <bndbox>
      <xmin>302</xmin>
      <ymin>385</ymin>
      <xmax>355</xmax>
      <ymax>517</ymax>
    </bndbox>
  </object>
  <object>
    <name>pedestrian</name>
    <pose>Unspecified</pose>
    <difficult>0</difficult>
    <truncated>0</truncated>
    <bndbox>
      <xmin>280</xmin>
      <ymin>380</ymin>
      <xmax>337</xmax>
      <ymax>520</ymax>
    </bndbox>
  </object>
  <object>
    <name>pedestrian</name>
    <pose>Unspecified</pose>
    <difficult>0</difficult>
    <truncated>0</truncated>
    <bndbox>
      <xmin>249</xmin>
      <ymin>392</ymin>
      <xmax>275</xmax>
      <ymax>457</ymax>
    </bndbox>
  </object>
  <object>
    <name>pedestrian</name>
    <pose>Unspecified</pose>
    <difficult>0</difficult>
    <truncated>0</truncated>
    <bndbox>
      <xmin>255</xmin>
      <ymin>413</ymin>
      <xmax>283</xmax>
      <ymax>485</ymax>
    </bndbox>
  </object>
  <object>
    <name>pedestrian</name>
    <pose>Unspecified</pose>
    <difficult>0</difficult>
    <truncated>0</truncated>
    <bndbox>
      <xmin>114</xmin>
      <ymin>393</ymin>
      <xmax>139</xmax>
      <ymax>456</ymax>
    </bndbox>
  </object>
  <object>
    <name>pedestrian</name>
    <pose>Unspecified</pose>
    <difficult>0</difficult>
    <truncated>0</truncated>
    <bndbox>
      <xmin>182</xmin>
      <ymin>381</ymin>
      <xmax>211</xmax>
      <ymax>454</ymax>
    </bndbox>
  </object>
  <object>
    <name>pedestrian</name>
    <pose>Unspecified</pose>
    <difficult>0</difficult>
    <truncated>0</truncated>
    <bndbox>
      <xmin>210</xmin>
      <ymin>383</ymin>
      <xmax>252</xmax>
      <ymax>489</ymax>
    </bndbox>
  </object>
  <object>
    <name>pedestrian</name>
    <pose>Unspecified</pose>
    <difficult>0</difficult>
    <truncated>0</truncated>
    <bndbox>
      <xmin>182</xmin>
      <ymin>382</ymin>
      <xmax>246</xmax>
      <ymax>540</ymax>
    </bndbox>
  </object>
  <object>
    <name>pedestrian</name>
    <pose>Unspecified</pose>
    <difficult>0</difficult>
    <truncated>0</truncated>
    <bndbox>
      <xmin>169</xmin>
      <ymin>384</ymin>
      <xmax>236</xmax>
      <ymax>548</ymax>
    </bndbox>
  </object>
  <object>
    <name>pedestrian</name>
    <pose>Unspecified</pose>
    <difficult>0</difficult>
    <truncated>0</truncated>
    <bndbox>
      <xmin>116</xmin>
      <ymin>382</ymin>
      <xmax>183</xmax>
      <ymax>546</ymax>
    </bndbox>
  </object>
  <object>
    <name>pedestrian</name>
    <pose>Unspecified</pose>
    <difficult>0</difficult>
    <truncated>0</truncated>
    <bndbox>
      <xmin>61</xmin>
      <ymin>376</ymin>
      <xmax>100</xmax>
      <ymax>475</ymax>
    </bndbox>
  </object>
  <object>
    <name>pedestrian</name>
    <pose>Unspecified</pose>
    <difficult>0</difficult>
    <truncated>1</truncated>
    <bndbox>
      <xmin>68</xmin>
      <ymin>386</ymin>
      <xmax>106</xmax>
      <ymax>482</ymax>
    </bndbox>
  </object>
  <object>
    <name>pedestrian</name>
    <pose>Unspecified</pose>
    <difficult>0</difficult>
    <truncated>0</truncated>
    <bndbox>
      <xmin>0</xmin>
      <ymin>398</ymin>
      <xmax>17</xmax>
      <ymax>471</ymax>
    </bndbox>
  </object>
  <object>
    <name>pedestrian</name>
    <pose>Unspecified</pose>
    <difficult>0</difficult>
    <truncated>1</truncated>
    <bndbox>
      <xmin>21</xmin>
      <ymin>383</ymin>
      <xmax>60</xmax>
      <ymax>479</ymax>
    </bndbox>
  </object>
  <object>
    <name>pedestrian</name>
    <pose>Unspecified</pose>
    <difficult>0</difficult>
    <truncated>1</truncated>
    <bndbox>
      <xmin>1543</xmin>
      <ymin>394</ymin>
      <xmax>1552</xmax>
      <ymax>407</ymax>
    </bndbox>
  </object>
  <object>
    <name>pedestrian</name>
    <pose>Unspecified</pose>
    <difficult>0</difficult>
    <truncated>1</truncated>
    <bndbox>
      <xmin>1528</xmin>
      <ymin>396</ymin>
      <xmax>1550</xmax>
      <ymax>412</ymax>
    </bndbox>
  </object>
  <object>
    <name>pedestrian</name>
    <pose>Unspecified</pose>
    <difficult>0</difficult>
    <truncated>0</truncated>
    <bndbox>
      <xmin>1842</xmin>
      <ymin>351</ymin>
      <xmax>1872</xmax>
      <ymax>426</ymax>
    </bndbox>
  </object>
  <object>
    <name>pedestrian</name>
    <pose>Unspecified</pose>
    <difficult>0</difficult>
    <truncated>0</truncated>
    <bndbox>
      <xmin>483</xmin>
      <ymin>428</ymin>
      <xmax>491</xmax>
      <ymax>448</ymax>
    </bndbox>
  </object>
  <object>
    <name>pedestrian</name>
    <pose>Unspecified</pose>
    <difficult>0</difficult>
    <truncated>0</truncated>
    <bndbox>
      <xmin>500</xmin>
      <ymin>451</ymin>
      <xmax>500</xmax>
      <ymax>451</ymax>
    </bndbox>
  </object>
  <object>
    <name>pedestrian</name>
    <pose>Unspecified</pose>
    <difficult>0</difficult>
    <truncated>0</truncated>
    <bndbox>
      <xmin>559</xmin>
      <ymin>431</ymin>
      <xmax>564</xmax>
      <ymax>451</ymax>
    </bndbox>
  </object>
  <object>
    <name>pedestrian</name>
    <pose>Unspecified</pose>
    <difficult>0</difficult>
    <truncated>0</truncated>
    <bndbox>
      <xmin>566</xmin>
      <ymin>446</ymin>
      <xmax>567</xmax>
      <ymax>451</ymax>
    </bndbox>
  </object>
  <object>
    <name>pedestrian</name>
    <pose>Unspecified</pose>
    <difficult>0</difficult>
    <truncated>0</truncated>
    <bndbox>
      <xmin>576</xmin>
      <ymin>441</ymin>
      <xmax>582</xmax>
      <ymax>451</ymax>
    </bndbox>
  </object>
  <object>
    <name>pedestrian</name>
    <pose>Unspecified</pose>
    <difficult>0</difficult>
    <truncated>0</truncated>
    <bndbox>
      <xmin>584</xmin>
      <ymin>451</ymin>
      <xmax>584</xmax>
      <ymax>451</ymax>
    </bndbox>
  </object>
  <object>
    <name>pedestrian</name>
    <pose>Unspecified</pose>
    <difficult>0</difficult>
    <truncated>0</truncated>
    <bndbox>
      <xmin>595</xmin>
      <ymin>437</ymin>
      <xmax>604</xmax>
      <ymax>450</ymax>
    </bndbox>
  </object>
  <object>
    <name>pedestrian</name>
    <pose>Unspecified</pose>
    <difficult>0</difficult>
    <truncated>0</truncated>
    <bndbox>
      <xmin>614</xmin>
      <ymin>449</ymin>
      <xmax>616</xmax>
      <ymax>450</ymax>
    </bndbox>
  </object>
  <object>
    <name>pedestrian</name>
    <pose>Unspecified</pose>
    <difficult>0</difficult>
    <truncated>0</truncated>
    <bndbox>
      <xmin>618</xmin>
      <ymin>417</ymin>
      <xmax>631</xmax>
      <ymax>450</ymax>
    </bndbox>
  </object>
  <object>
    <name>pedestrian</name>
    <pose>Unspecified</pose>
    <difficult>0</difficult>
    <truncated>0</truncated>
    <bndbox>
      <xmin>1289</xmin>
      <ymin>387</ymin>
      <xmax>1306</xmax>
      <ymax>434</ymax>
    </bndbox>
  </object>
  <object>
    <name>pedestrian</name>
    <pose>Unspecified</pose>
    <difficult>0</difficult>
    <truncated>0</truncated>
    <bndbox>
      <xmin>1352</xmin>
      <ymin>391</ymin>
      <xmax>1387</xmax>
      <ymax>432</ymax>
    </bndbox>
  </object>
  <object>
    <name>pedestrian</name>
    <pose>Unspecified</pose>
    <difficult>0</difficult>
    <truncated>0</truncated>
    <bndbox>
      <xmin>1683</xmin>
      <ymin>369</ymin>
      <xmax>1699</xmax>
      <ymax>431</ymax>
    </bndbox>
  </object>
  <object>
    <name>pedestrian</name>
    <pose>Unspecified</pose>
    <difficult>0</difficult>
    <truncated>0</truncated>
    <bndbox>
      <xmin>1720</xmin>
      <ymin>381</ymin>
      <xmax>1730</xmax>
      <ymax>425</ymax>
    </bndbox>
  </object>
  <object>
    <name>pedestrian</name>
    <pose>Unspecified</pose>
    <difficult>0</difficult>
    <truncated>0</truncated>
    <bndbox>
      <xmin>1721</xmin>
      <ymin>353</ymin>
      <xmax>1730</xmax>
      <ymax>367</ymax>
    </bndbox>
  </object>
</annotation>
