<annotation>
  <folder>VOC2007</folder>
  <filename>hamburg_000000_020563.png</filename>
  <size>
    <width>2048</width>
    <height>1024</height>
    <depth>3</depth>
  </size>
  <object>
    <name>pedestrian</name>
    <pose>Unspecified</pose>
    <difficult>0</difficult>
    <truncated>0</truncated>
    <bndbox>
      <xmin>1782</xmin>
      <ymin>394</ymin>
      <xmax>1801</xmax>
      <ymax>441</ymax>
    </bndbox>
  </object>
  <object>
    <name>pedestrian</name>
    <pose>Unspecified</pose>
    <difficult>0</difficult>
    <truncated>0</truncated>
    <bndbox>
      <xmin>2015</xmin>
      <ymin>378</ymin>
      <xmax>2047</xmax>
      <ymax>475</ymax>
    </bndbox>
  </object>
</annotation>
