<annotation>
  <folder>VOC2007</folder>
  <filename>hanover_000000_022645.png</filename>
  <size>
    <width>2048</width>
    <height>1024</height>
    <depth>3</depth>
  </size>
  <object>
    <name>pedestrian</name>
    <pose>Unspecified</pose>
    <difficult>0</difficult>
    <truncated>0</truncated>
    <bndbox>
      <xmin>256</xmin>
      <ymin>401</ymin>
      <xmax>276</xmax>
      <ymax>452</ymax>
    </bndbox>
  </object>
  <object>
    <name>pedestrian</name>
    <pose>Unspecified</pose>
    <difficult>0</difficult>
    <truncated>0</truncated>
    <bndbox>
      <xmin>221</xmin>
      <ymin>400</ymin>
      <xmax>242</xmax>
      <ymax>452</ymax>
    </bndbox>
  </object>
  <object>
    <name>pedestrian</name>
    <pose>Unspecified</pose>
    <difficult>0</difficult>
    <truncated>0</truncated>
    <bndbox>
      <xmin>112</xmin>
      <ymin>401</ymin>
      <xmax>133</xmax>
      <ymax>452</ymax>
    </bndbox>
  </object>
</annotation>
