<annotation>
  <folder>VOC2007</folder>
  <filename>weimar_000026_000019.png</filename>
  <size>
    <width>2048</width>
    <height>1024</height>
    <depth>3</depth>
  </size>
  <object>
    <name>ped</name>
    <pose>Unspecified</pose>
    <difficult>0</difficult>
    <truncated>0</truncated>
    <bndbox>
      <xmin>974</xmin>
      <ymin>452</ymin>
      <xmax>1017</xmax>
      <ymax>556</ymax>
    </bndbox>
  </object>
  <object>
    <name>ped</name>
    <pose>Unspecified</pose>
    <difficult>0</difficult>
    <truncated>0</truncated>
    <bndbox>
      <xmin>874</xmin>
      <ymin>430</ymin>
      <xmax>935</xmax>
      <ymax>582</ymax>
    </bndbox>
  </object>
  <object>
    <name>ped</name>
    <pose>Unspecified</pose>
    <difficult>0</difficult>
    <truncated>0</truncated>
    <bndbox>
      <xmin>921</xmin>
      <ymin>435</ymin>
      <xmax>982</xmax>
      <ymax>585</ymax>
    </bndbox>
  </object>
  <object>
    <name>ped</name>
    <pose>Unspecified</pose>
    <difficult>0</difficult>
    <truncated>0</truncated>
    <bndbox>
      <xmin>807</xmin>
      <ymin>389</ymin>
      <xmax>894</xmax>
      <ymax>603</ymax>
    </bndbox>
  </object>
  <object>
    <name>ped</name>
    <pose>Unspecified</pose>
    <difficult>0</difficult>
    <truncated>1</truncated>
    <bndbox>
      <xmin>1070</xmin>
      <ymin>454</ymin>
      <xmax>1112</xmax>
      <ymax>559</ymax>
    </bndbox>
  </object>
  <object>
    <name>ped</name>
    <pose>Unspecified</pose>
    <difficult>0</difficult>
    <truncated>0</truncated>
    <bndbox>
      <xmin>1641</xmin>
      <ymin>402</ymin>
      <xmax>1741</xmax>
      <ymax>649</ymax>
    </bndbox>
  </object>
</annotation>
