<annotation>
  <folder>VOC2007</folder>
  <filename>zurich_000030_000019.png</filename>
  <size>
    <width>2048</width>
    <height>1024</height>
    <depth>3</depth>
  </size>
  <object>
    <name>pedestrian</name>
    <pose>Unspecified</pose>
    <difficult>0</difficult>
    <truncated>0</truncated>
    <bndbox>
      <xmin>1569</xmin>
      <ymin>294</ymin>
      <xmax>1725</xmax>
      <ymax>674</ymax>
    </bndbox>
  </object>
  <object>
    <name>pedestrian</name>
    <pose>Unspecified</pose>
    <difficult>0</difficult>
    <truncated>0</truncated>
    <bndbox>
      <xmin>1525</xmin>
      <ymin>336</ymin>
      <xmax>1673</xmax>
      <ymax>697</ymax>
    </bndbox>
  </object>
  <object>
    <name>pedestrian</name>
    <pose>Unspecified</pose>
    <difficult>0</difficult>
    <truncated>1</truncated>
    <bndbox>
      <xmin>139</xmin>
      <ymin>391</ymin>
      <xmax>251</xmax>
      <ymax>663</ymax>
    </bndbox>
  </object>
  <object>
    <name>pedestrian</name>
    <pose>Unspecified</pose>
    <difficult>0</difficult>
    <truncated>0</truncated>
    <bndbox>
      <xmin>629</xmin>
      <ymin>330</ymin>
      <xmax>781</xmax>
      <ymax>703</ymax>
    </bndbox>
  </object>
  <object>
    <name>pedestrian</name>
    <pose>Unspecified</pose>
    <difficult>0</difficult>
    <truncated>0</truncated>
    <bndbox>
      <xmin>775</xmin>
      <ymin>366</ymin>
      <xmax>889</xmax>
      <ymax>647</ymax>
    </bndbox>
  </object>
  <object>
    <name>pedestrian</name>
    <pose>Unspecified</pose>
    <difficult>0</difficult>
    <truncated>1</truncated>
    <bndbox>
      <xmin>808</xmin>
      <ymin>424</ymin>
      <xmax>919</xmax>
      <ymax>695</ymax>
    </bndbox>
  </object>
  <object>
    <name>pedestrian</name>
    <pose>Unspecified</pose>
    <difficult>0</difficult>
    <truncated>0</truncated>
    <bndbox>
      <xmin>713</xmin>
      <ymin>320</ymin>
      <xmax>824</xmax>
      <ymax>592</ymax>
    </bndbox>
  </object>
  <object>
    <name>pedestrian</name>
    <pose>Unspecified</pose>
    <difficult>0</difficult>
    <truncated>1</truncated>
    <bndbox>
      <xmin>1560</xmin>
      <ymin>295</ymin>
      <xmax>1742</xmax>
      <ymax>739</ymax>
    </bndbox>
  </object>
</annotation>
